configs.py
manage.py
aishowapp/__init__.py
aishowapp/baseclient.py
aishowapp/ext.py
aishowapp/serializer.py
aishowapp/until.py
aishowapp/apis/__init__.py
aishowapp/apis/auth_api.py
aishowapp/apis/base.py
aishowapp/apis/goods_api.py
aishowapp/apis/mcn_pat_api.py
aishowapp/apis/paltformliveshow_api.py
aishowapp/apis/rbac_api.py
aishowapp/apis/res_bkl.py
aishowapp/apis/resource_api.py
aishowapp/apis/search_api.py
aishowapp/apis/show_api.py
aishowapp/core/__init__.py
aishowapp/core/constants.py
aishowapp/core/exceptions.py
aishowapp/core/utils.py
aishowapp/models/__init__.py
aishowapp/models/ai_star.py
aishowapp/models/mcn_pat.py
aishowapp/models/mmm.py
aishowapp/models/new_resource_model.py
aishowapp/models/rbac.py
aishowapp/models/resource_model.py
aishowapp/storage/__init__.py
aishowapp/storage/cache.py
aishowapp/storage/kvstorage.py
aishowapp/storage/memorystorage.py
zly_resource-1.1.8.dist-info/METADATA
zly_resource-1.1.8.dist-info/WHEEL
zly_resource-1.1.8.dist-info/top_level.txt
zly_resource-1.1.8.dist-info/RECORD
