Metadata-Version: 2.1
Name: zly-resource
Version: 1.1.8
Summary: resource SDK for Python
Home-page: UNKNOWN
License: MIT
Keywords: aishow,,SDK
Platform: UNKNOWN
Classifier: Programming Language :: Python :: 3
Classifier: License :: OSI Approved :: MIT License
Classifier: Operating System :: OS Independent
Requires-Python: >=3.6
Requires-Dist: six (>=1.8.0)
Requires-Dist: requests (>=2.4.3)
Requires-Dist: optionaldict (>=0.1.0)
Requires-Dist: flake8 (>=3.4.1)
Requires-Dist: Flask (>=1.1.1)
Requires-Dist: Flask-Bootstrap (>=3.3.7.1)
Requires-Dist: Flask-Caching (>=1.8.0)
Requires-Dist: Flask-Cors (>=3.0.8)
Requires-Dist: Flask-Login (>=0.5.0)
Requires-Dist: Flask-Mail (>=0.9.1)
Requires-Dist: Flask-Migrate (>=2.5.2)
Requires-Dist: Flask-Moment (>=0.9.0)
Requires-Dist: Flask-PageDown (>=0.2.2)
Requires-Dist: flask-redis (>=0.4.0)
Requires-Dist: Flask-RESTful (>=0.3.7)
Requires-Dist: Flask-Script (>=2.0.6)
Requires-Dist: Flask-Session (>=0.3.1)
Requires-Dist: Flask-SQLAlchemy (>=2.4.1)
Requires-Dist: Flask-SSLify (>=0.1.5)
Requires-Dist: enum34 (>=1.1.4) ; python_version < "3.4"
